brange/__init__.py
brange/brange.py
brange/nbrange.py
brange-1.1.0.post1.dist-info/WHEEL
brange-1.1.0.post1.dist-info/METADATA
brange-1.1.0.post1.dist-info/RECORD
