Metadata-Version: 2.1
Name: brange
Version: 1.1.0.post1
Summary: A range which automatically deals with either direction.
Home-page: https://gitlab.com/deepadmax/brange
Author: Maximillian Strand
Author-email: maximillian.strand@protonmail.com
Requires-Python: >=3.9,<4.0
Classifier: Programming Language :: Python :: 3
Classifier: Programming Language :: Python :: 3.9
